yeref/__init__.py
yeref/l_.py
yeref/tonweb.js
yeref/yeref.py
yeref-0.30.94.dist-info/METADATA
yeref-0.30.94.dist-info/WHEEL
yeref-0.30.94.dist-info/top_level.txt
yeref-0.30.94.dist-info/RECORD
