Metadata-Version: 2.4
Name: yeref
Version: 0.30.94
Summary: desc-f
Author: john smith
Dynamic: author
Dynamic: summary
